{"type":"FeatureCollection","crs":{"type":"name","properties":{"name":"urn:ogc:def:crs:OGC:1.3:CRS84"}},"features":[{"type":"Feature","geometry":{"type":"Point","coordinates":[-46.659578,-23.559082]},"properties":{"id":"1","subprefeitura":"Pinheiros","proponente":"Instituto Mobilidade Verde","telefone":"(11) 99435-5187","email":"lp@mobilidadeverde.org.","localizacao":"Rua Padre João Manoel, 47","inicio_cooperacao":"23/05/2014","termino_cooperacao":"23/05/2017","":"","solicitacao":"ok","conhecimento_publico":"ok","chamamento":"","aprovado":"23/05/2014","construido":"16/04/2014","removido":"","data_evento":"","status":2}},{"type":"Feature","geometry":{"type":"Point","coordinates":[-46.646316,-23.574496]},"properties":{"id":"2","subprefeitura":"Vila Mariana","proponente":"Instituto Mobilidade Verde (?)","telefone":"(11) 99435-5187","email":"lp@mobilidadeverde.org.","localizacao":"Rua Coronel Oscar Porto, 634","inicio_cooperacao":"?","termino_cooperacao":"?","":"","solicitacao":"","conhecimento_publico":"","chamamento":"","aprovado":"","construido":"13/08/2014","removido":"","data_evento":"","status":2}},{"type":"Feature","geometry":{"type":"Point","coordinates":[-46.689303,-23.55694]},"properties":{"id":"3","subprefeitura":"Pinheiros","proponente":"Aspicuelta 422 Empreendimentos Ltda","telefone":"(11) 99435-5187","email":"lp@mobilidadeverde.org.","localizacao":"Rua Fidalga, 245","inicio_cooperacao":"15/08/2014","termino_cooperacao":"15/08/2017","":"","solicitacao":"3/6/2014","conhecimento_publico":"05/06 a 19/06/2014","chamamento":"","aprovado":"12/8/2014","construido":"13/08/2014","removido":"","data_evento":"","status":2}},{"type":"Feature","geometry":{"type":"Point","coordinates":[-46.699614,-23.551153]},"properties":{"id":"5","subprefeitura":"Pinheiros","proponente":"Contain' it Industria","telefone":"(11) 99435-5187","email":"lp@mobilidadeverde.org.","localizacao":"Rua Isabel de Castela, 529","inicio_cooperacao":"15/08/2014","termino_cooperacao":"15/08/2017","":"","solicitacao":"16/7/2014","conhecimento_publico":"18/07 a 31/07/2014","chamamento":"","aprovado":"12/8/0914","construido":"13/08/2014","removido":"","data_evento":"","status":2}},{"type":"Feature","geometry":{"type":"Point","coordinates":[-46.680491,-23.562225]},"properties":{"id":"11","subprefeitura":"Pinheiros","proponente":"Instituto Mobilidade Verde","telefone":"(11) 99435-5187","email":"lp@mobilidadeverde.org.","localizacao":"Rua Francisco Leitão, 282","inicio_cooperacao":"24/09/2014","termino_cooperacao":"24/09/2017","":"","solicitacao":"31/08/2014","conhecimento_publico":"01/09 a 12/09/2014","chamamento":"","aprovado":"24/09/2014","construido":"25/09/2014","removido":"","data_evento":"","status":2}}]}